<?xml version="1.0" encoding="utf-8"?>
<p:FatturaElettronica versione="FPR12" xmlns:ds="http://www.w3.org/2000/09/xmldsig#" xmlns:xsi="http://www.w3.org/2001/XMLSchema-instance" xsi:schemaLocation="http://ivaservizi.agenziaentrate.gov.it/docs/xsd/fatture/v1.2 fatturaordinaria_v1.2.xsd" xmlns:p="http://ivaservizi.agenziaentrate.gov.it/docs/xsd/fatture/v1.2">
  <FatturaElettronicaHeader>
    <DatiTrasmissione>
      <IdTrasmittente>
        <IdPaese>IT</IdPaese>
        <IdCodice>01879020517</IdCodice>
      </IdTrasmittente>
      <ProgressivoInvio>28</ProgressivoInvio>
      <FormatoTrasmissione>FPR12</FormatoTrasmissione>
      <CodiceDestinatario>KRRH6B9</CodiceDestinatario>
    </DatiTrasmissione>
    <CedentePrestatore>
      <DatiAnagrafici>
        <IdFiscaleIVA>
          <IdPaese>IT</IdPaese>
          <IdCodice>04012320612</IdCodice>
        </IdFiscaleIVA>
        <CodiceFiscale>FRTVLR78S04H501W</CodiceFiscale>
        <Anagrafica>
          <Denominazione>Valerio Fiorito</Denominazione>
        </Anagrafica>
        <RegimeFiscale>RF01</RegimeFiscale>
      </DatiAnagrafici>
      <Sede>
        <Indirizzo>Via Roma</Indirizzo>
        <NumeroCivico>174</NumeroCivico>
        <CAP>81100</CAP>
        <Comune>Caserta</Comune>
        <Provincia>CE</Provincia>
        <Nazione>IT</Nazione>
      </Sede>
      <Contatti>
        <Telefono>08231541097</Telefono>
        <Fax>08231541097</Fax>
        <Email>info@smartinglab.it</Email>
      </Contatti>
    </CedentePrestatore>
    <CessionarioCommittente>
      <DatiAnagrafici>
        <IdFiscaleIVA>
          <IdPaese>IT</IdPaese>
          <IdCodice>05744121210</IdCodice>
        </IdFiscaleIVA>
        <CodiceFiscale>05744121210</CodiceFiscale>
        <Anagrafica>
          <Denominazione>R&amp;B CONSULTING SRL</Denominazione>
        </Anagrafica>
      </DatiAnagrafici>
      <Sede>
        <Indirizzo>VIA CRESCENZIO, 25</Indirizzo>
        <CAP>00193</CAP>
        <Comune>ROMA</Comune>
        <Provincia>RM</Provincia>
        <Nazione>IT</Nazione>
      </Sede>
    </CessionarioCommittente>
  </FatturaElettronicaHeader>
  <FatturaElettronicaBody>
    <DatiGenerali>
      <DatiGeneraliDocumento>
        <TipoDocumento>TD01</TipoDocumento>
        <Divisa>EUR</Divisa>
        <Data>2021-09-03</Data>
        <Numero>FPR 28/21</Numero>
        <ImportoTotaleDocumento>80.00</ImportoTotaleDocumento>
      </DatiGeneraliDocumento>
    </DatiGenerali>
    <DatiBeniServizi>
      <DettaglioLinee>
        <NumeroLinea>1</NumeroLinea>
        <Descrizione>RIPARAZIONE APPLE IPHONE X </Descrizione>
        <Quantita>1.00</Quantita>
        <PrezzoUnitario>65.57</PrezzoUnitario>
        <PrezzoTotale>65.57</PrezzoTotale>
        <AliquotaIVA>22.00</AliquotaIVA>
      </DettaglioLinee>
      <DatiRiepilogo>
        <AliquotaIVA>22.00</AliquotaIVA>
        <ImponibileImporto>65.57</ImponibileImporto>
        <Imposta>14.43</Imposta>
      </DatiRiepilogo>
    </DatiBeniServizi>
    <DatiPagamento>
      <CondizioniPagamento>TP02</CondizioniPagamento>
      <DettaglioPagamento>
        <ModalitaPagamento>MP08</ModalitaPagamento>
        <DataScadenzaPagamento>2021-09-03</DataScadenzaPagamento>
        <ImportoPagamento>80.00</ImportoPagamento>
      </DettaglioPagamento>
    </DatiPagamento>
  </FatturaElettronicaBody>
</p:FatturaElettronica>