<?xml version="1.0" encoding="utf-8" standalone="no"?><p:FatturaElettronica versione="FPR12" xmlns:ds="http://www.w3.org/2000/09/xmldsig#" xmlns:p="http://ivaservizi.agenziaentrate.gov.it/docs/xsd/fatture/v1.2" xmlns:xsi="http://www.w3.org/2001/XMLSchema-instance" xsi:schemaLocation="http://ivaservizi.agenziaentrate.gov.it/docs/xsd/fatture/v1.2 http://www.fatturapa.gov.it/export/fatturazione/sdi/fatturapa/v1.2/Schema_del_file_xml_FatturaPA_versione_1.2.xsd">
  <FatturaElettronicaHeader>
    <DatiTrasmissione>
      <IdTrasmittente>
        <IdPaese>IT</IdPaese>
        <IdCodice>04077341008</IdCodice>
      </IdTrasmittente>
      <ProgressivoInvio>8YBSO</ProgressivoInvio>
      <FormatoTrasmissione>FPR12</FormatoTrasmissione>
      <CodiceDestinatario>KRRH6V9</CodiceDestinatario>
    </DatiTrasmissione>
    <CedentePrestatore>
      <DatiAnagrafici>
        <IdFiscaleIVA>
          <IdPaese>IT</IdPaese>
          <IdCodice>09060061216</IdCodice>
        </IdFiscaleIVA>
        <CodiceFiscale>09060061216</CodiceFiscale>
        <Anagrafica>
          <Denominazione>Manzoni 308 srl</Denominazione>
        </Anagrafica>
        <RegimeFiscale>RF01</RegimeFiscale>
      </DatiAnagrafici>
      <Sede>
        <Indirizzo>Via Manzoni</Indirizzo>
        <NumeroCivico>308</NumeroCivico>
        <CAP>80123</CAP>
        <Comune>Napoli</Comune>
        <Provincia>NA</Provincia>
        <Nazione>IT</Nazione>
      </Sede>
      <Contatti>
        <Telefono>081625267</Telefono>
      </Contatti>
    </CedentePrestatore>
    <CessionarioCommittente>
      <DatiAnagrafici>
        <IdFiscaleIVA>
          <IdPaese>IT</IdPaese>
          <IdCodice>05744121210</IdCodice>
        </IdFiscaleIVA>
        <Anagrafica>
          <Denominazione>RB consulting </Denominazione>
        </Anagrafica>
      </DatiAnagrafici>
      <Sede>
        <Indirizzo>Via crescenzio  25</Indirizzo>
        <CAP>00164</CAP>
        <Comune>Roma</Comune>
        <Provincia>RM</Provincia>
        <Nazione>IT</Nazione>
      </Sede>
    </CessionarioCommittente>
  </FatturaElettronicaHeader>
  <FatturaElettronicaBody>
    <DatiGenerali>
      <DatiGeneraliDocumento>
        <TipoDocumento>TD01</TipoDocumento>
        <Divisa>EUR</Divisa>
        <Data>2022-01-13</Data>
        <Numero>312</Numero>
        <ImportoTotaleDocumento>600.00</ImportoTotaleDocumento>
      </DatiGeneraliDocumento>
    </DatiGenerali>
    <DatiBeniServizi>
      <DettaglioLinee>
        <NumeroLinea>1</NumeroLinea>
        <Descrizione>Servizio 10%</Descrizione>
        <Quantita>6.00</Quantita>
        <PrezzoUnitario>9.09090909</PrezzoUnitario>
        <ScontoMaggiorazione>
          <Tipo>SC</Tipo>
          <Importo>0.82666667</Importo>
        </ScontoMaggiorazione>
        <PrezzoTotale>49.58545452</PrezzoTotale>
        <AliquotaIVA>10.00</AliquotaIVA>
      </DettaglioLinee>
      <DettaglioLinee>
        <NumeroLinea>2</NumeroLinea>
        <Descrizione>Evento 6 pax</Descrizione>
        <Quantita>1.00</Quantita>
        <PrezzoUnitario>545.45454545</PrezzoUnitario>
        <ScontoMaggiorazione>
          <Tipo>SC</Tipo>
          <Importo>49.59000000</Importo>
        </ScontoMaggiorazione>
        <PrezzoTotale>495.86454545</PrezzoTotale>
        <AliquotaIVA>10.00</AliquotaIVA>
      </DettaglioLinee>
      <DatiRiepilogo>
        <AliquotaIVA>10.00</AliquotaIVA>
        <Arrotondamento>0.00000003</Arrotondamento>
        <ImponibileImporto>545.45</ImponibileImporto>
        <Imposta>54.55</Imposta>
      </DatiRiepilogo>
    </DatiBeniServizi>
    <DatiPagamento>
      <CondizioniPagamento>TP02</CondizioniPagamento>
      <DettaglioPagamento>
        <ModalitaPagamento>MP08</ModalitaPagamento>
        <ImportoPagamento>600.00</ImportoPagamento>
      </DettaglioPagamento>
    </DatiPagamento>
  </FatturaElettronicaBody>
</p:FatturaElettronica>