<ns2:FatturaElettronica xmlns:ns2="http://ivaservizi.agenziaentrate.gov.it/docs/xsd/fatture/v1.2" versione="FPR12">
   <FatturaElettronicaHeader>
      <DatiTrasmissione><IdTrasmittente><IdPaese>IT</IdPaese><IdCodice>08973230967</IdCodice></IdTrasmittente><ProgressivoInvio>1OC7k</ProgressivoInvio><FormatoTrasmissione>FPR12</FormatoTrasmissione><CodiceDestinatario>0000000</CodiceDestinatario></DatiTrasmissione>
      <CedentePrestatore>
         <DatiAnagrafici>
            <IdFiscaleIVA>
               <IdPaese>IT</IdPaese>
               <IdCodice>03632200543</IdCodice>
            </IdFiscaleIVA>
            <Anagrafica>
               <Denominazione>Thousandshores Deutschland GmbH</Denominazione>
            </Anagrafica>
            <RegimeFiscale>RF01</RegimeFiscale>
         </DatiAnagrafici>
         <Sede>
            <Indirizzo>VIA SAN BARTOLOMEO 128</Indirizzo>
            <CAP>06135</CAP>
            <Comune>PERUGIA PG</Comune>
            <Nazione>IT</Nazione>
         </Sede>
      </CedentePrestatore>
      <CessionarioCommittente>
         <DatiAnagrafici>
            <IdFiscaleIVA>
               <IdPaese>IT</IdPaese>
               <IdCodice>05744121210</IdCodice>
            </IdFiscaleIVA>
            <Anagrafica>
               <Denominazione>R&amp;B Consulting Srl</Denominazione>
            </Anagrafica>
         </DatiAnagrafici>
         <Sede>
            <Indirizzo>Via Crescenzio, 25</Indirizzo>
            <CAP>00193</CAP>
            <Comune>Roma</Comune>
            <Nazione>IT</Nazione>
         </Sede>
      </CessionarioCommittente>
      <TerzoIntermediarioOSoggettoEmittente>
         <DatiAnagrafici>
            <IdFiscaleIVA>
               <IdPaese>IT</IdPaese>
               <IdCodice>00161809991</IdCodice>
            </IdFiscaleIVA>
            <Anagrafica>
               <Denominazione>Amazon Services Europe S.à r.l.</Denominazione>
            </Anagrafica>
         </DatiAnagrafici>
      </TerzoIntermediarioOSoggettoEmittente>
      <SoggettoEmittente>TZ</SoggettoEmittente>
   </FatturaElettronicaHeader>
   <FatturaElettronicaBody>
      <DatiGenerali>
         <DatiGeneraliDocumento>
            <TipoDocumento>TD01</TipoDocumento>
            <Divisa>EUR</Divisa>
            <Data>2019-09-18</Data>
            <Numero>IT19-70495I-1726</Numero>
            <ImportoTotaleDocumento>31.99</ImportoTotaleDocumento>
            <Arrotondamento>0.00</Arrotondamento>
         </DatiGeneraliDocumento>
         <DatiContratto>
            <RiferimentoNumeroLinea>1</RiferimentoNumeroLinea>
            <IdDocumento>406-3847241-2301160</IdDocumento>
            <Data>2019-09-18</Data>
         </DatiContratto>
         <FatturaPrincipale>
            <NumeroFatturaPrincipale>IT19-70495I-1726</NumeroFatturaPrincipale>
            <DataFatturaPrincipale>2019-09-18</DataFatturaPrincipale>
         </FatturaPrincipale>
      </DatiGenerali>
      <DatiBeniServizi>
         <DettaglioLinee>
            <NumeroLinea>1</NumeroLinea>
            <Descrizione>iclever Tastiera e Mouse Wireless - Tastiera e Mouse Portatili Wireless 2.4G, Batteria Ricaricabile Design Ergonomico Dimensioni Regolari Sottile Connessione Stabile DPI Regolabile (Argento e Bianco)</Descrizione>
            <Quantita>1.00</Quantita>
            <DataInizioPeriodo>2019-09-18</DataInizioPeriodo>
            <DataFinePeriodo>2019-09-18</DataFinePeriodo>
            <PrezzoUnitario>26.22</PrezzoUnitario>
            <PrezzoTotale>26.22</PrezzoTotale>
            <AliquotaIVA>22.00</AliquotaIVA>
         </DettaglioLinee>
         <DatiRiepilogo>
            <AliquotaIVA>22.00</AliquotaIVA>
            <Arrotondamento>0.01</Arrotondamento>
            <ImponibileImporto>26.23</ImponibileImporto>
            <Imposta>5.77</Imposta>
         </DatiRiepilogo>
      </DatiBeniServizi>
      <DatiPagamento>
         <CondizioniPagamento>TP02</CondizioniPagamento>
         <DettaglioPagamento>
            <ModalitaPagamento>MP08</ModalitaPagamento>
            <ImportoPagamento>31.99</ImportoPagamento>
         </DettaglioPagamento>
      </DatiPagamento>
   </FatturaElettronicaBody>
</ns2:FatturaElettronica>