<?xml version="1.0" encoding="UTF-8"?>
<p:FatturaElettronica xsi:schemaLocation="http://ivaservizi.agenziaentrate.gov.it/docs/xsd/fatture/v1.2 http://www.fatturapa.gov.it/export/fatturazione/sdi/fatturapa/v1.2/Schema_del_file_xml_FatturaPA_versione_1.2.xsd" xmlns:ds="http://www.w3.org/2000/09/xmldsig#" versione="FPR12" xmlns:xsi="http://www.w3.org/2001/XMLSchema-instance" xmlns:p="http://ivaservizi.agenziaentrate.gov.it/docs/xsd/fatture/v1.2">
  <FatturaElettronicaHeader>
    <DatiTrasmissione>
      <IdTrasmittente>
        <IdPaese>IT</IdPaese>
        <IdCodice>04747270611</IdCodice>
      </IdTrasmittente>
      <ProgressivoInvio>308</ProgressivoInvio>
      <FormatoTrasmissione>FPR12</FormatoTrasmissione>
      <CodiceDestinatario>KRRH6B9</CodiceDestinatario>
      <PECDestinatario>RBCONSULTINGSRL@PEC.IT</PECDestinatario>
    </DatiTrasmissione>
    <CedentePrestatore>
      <DatiAnagrafici>
        <IdFiscaleIVA>
          <IdPaese>IT</IdPaese>
          <IdCodice>04747270611</IdCodice>
        </IdFiscaleIVA>
        <Anagrafica>
          <Denominazione>CASANOVA S.R.L.</Denominazione>
        </Anagrafica>
        <RegimeFiscale>RF01</RegimeFiscale>
      </DatiAnagrafici>
      <Sede>
        <Indirizzo>VIA PAOLO BORSELLINO</Indirizzo>
        <NumeroCivico>SNC</NumeroCivico>
        <CAP>81100</CAP>
        <Comune>CASERTA</Comune>
        <Provincia>CE</Provincia>
        <Nazione>IT</Nazione>
      </Sede>
      <Contatti>
        <Telefono>3515555210</Telefono>
        <Email>HUYUNYOU@LIBERO.IT</Email>
      </Contatti>
    </CedentePrestatore>
    <CessionarioCommittente>
      <DatiAnagrafici>
        <IdFiscaleIVA>
          <IdPaese>IT</IdPaese>
          <IdCodice>17044041006</IdCodice>
        </IdFiscaleIVA>
        <Anagrafica>
          <Denominazione>RB CONSULTING SRL</Denominazione>
        </Anagrafica>
      </DatiAnagrafici>
      <Sede>
        <Indirizzo>VIA DEI VECCHI PINI ,13</Indirizzo>
        <CAP>81100</CAP>
        <Comune>CASERTA</Comune>
        <Provincia>CE</Provincia>
        <Nazione>IT</Nazione>
      </Sede>
    </CessionarioCommittente>
  </FatturaElettronicaHeader>
  <FatturaElettronicaBody>
    <DatiGenerali>
      <DatiGeneraliDocumento>
        <TipoDocumento>TD01</TipoDocumento>
        <Divisa>EUR</Divisa>
        <Data>2024-11-14</Data>
        <Numero>308</Numero>
        <ImportoTotaleDocumento>138.80</ImportoTotaleDocumento>
        <Causale>Vendita</Causale>
      </DatiGeneraliDocumento>
    </DatiGenerali>
    <DatiBeniServizi>
      <DettaglioLinee>
        <NumeroLinea>1</NumeroLinea>
        <CodiceArticolo>
          <CodiceTipo>EAN</CodiceTipo>
          <CodiceValore>8007633701818</CodiceValore>
        </CodiceArticolo>
        <Descrizione>PAGLIA CESTA BUCATO</Descrizione>
        <Quantita>1.0000</Quantita>
        <UnitaMisura>PZ</UnitaMisura>
        <PrezzoUnitario>7.3689</PrezzoUnitario>
        <PrezzoTotale>7.3689</PrezzoTotale>
        <AliquotaIVA>22.00</AliquotaIVA>
      </DettaglioLinee>
      <DettaglioLinee>
        <NumeroLinea>2</NumeroLinea>
        <CodiceArticolo>
          <CodiceTipo>EAN</CodiceTipo>
          <CodiceValore>8058266161586</CodiceValore>
        </CodiceArticolo>
        <Descrizione>SCOPA CATTURAPOPVERE </Descrizione>
        <Quantita>1.0000</Quantita>
        <UnitaMisura>PZ</UnitaMisura>
        <PrezzoUnitario>5.6557</PrezzoUnitario>
        <PrezzoTotale>5.6557</PrezzoTotale>
        <AliquotaIVA>22.00</AliquotaIVA>
      </DettaglioLinee>
      <DettaglioLinee>
        <NumeroLinea>3</NumeroLinea>
        <CodiceArticolo>
          <CodiceTipo>EAN</CodiceTipo>
          <CodiceValore>8003650019776</CodiceValore>
        </CodiceArticolo>
        <Descrizione>OMINO BIANCO CANDEGGINA 2LT BREZZA M.</Descrizione>
        <Quantita>1.0000</Quantita>
        <UnitaMisura>PZ</UnitaMisura>
        <PrezzoUnitario>2.2951</PrezzoUnitario>
        <PrezzoTotale>2.2951</PrezzoTotale>
        <AliquotaIVA>22.00</AliquotaIVA>
      </DettaglioLinee>
      <DettaglioLinee>
        <NumeroLinea>4</NumeroLinea>
        <CodiceArticolo>
          <CodiceTipo>EAN</CodiceTipo>
          <CodiceValore>8003650000798</CodiceValore>
        </CodiceArticolo>
        <Descrizione>SMAC GEL CANDEGGINA ML.850</Descrizione>
        <Quantita>1.0000</Quantita>
        <UnitaMisura>PZ</UnitaMisura>
        <PrezzoUnitario>1.2295</PrezzoUnitario>
        <PrezzoTotale>1.2295</PrezzoTotale>
        <AliquotaIVA>22.00</AliquotaIVA>
      </DettaglioLinee>
      <DettaglioLinee>
        <NumeroLinea>5</NumeroLinea>
        <CodiceArticolo>
          <CodiceTipo>EAN</CodiceTipo>
          <CodiceValore>8015194522506</CodiceValore>
        </CodiceArticolo>
        <Descrizione>CHANTE CLAIR AMMORBIDENTE 57 DOSI 1,14 LT SALI/LOT</Descrizione>
        <Quantita>1.0000</Quantita>
        <UnitaMisura>PZ</UnitaMisura>
        <PrezzoUnitario>1.9672</PrezzoUnitario>
        <PrezzoTotale>1.9672</PrezzoTotale>
        <AliquotaIVA>22.00</AliquotaIVA>
      </DettaglioLinee>
      <DettaglioLinee>
        <NumeroLinea>6</NumeroLinea>
        <CodiceArticolo>
          <CodiceTipo>EAN</CodiceTipo>
          <CodiceValore>8015194522506</CodiceValore>
        </CodiceArticolo>
        <Descrizione>CHANTE CLAIR AMMORBIDENTE 57 DOSI 1,14 LT SALI/LOT</Descrizione>
        <Quantita>1.0000</Quantita>
        <UnitaMisura>PZ</UnitaMisura>
        <PrezzoUnitario>1.9672</PrezzoUnitario>
        <PrezzoTotale>1.9672</PrezzoTotale>
        <AliquotaIVA>22.00</AliquotaIVA>
      </DettaglioLinee>
      <DettaglioLinee>
        <NumeroLinea>7</NumeroLinea>
        <CodiceArticolo>
          <CodiceTipo>EAN</CodiceTipo>
          <CodiceValore>8001480709089</CodiceValore>
        </CodiceArticolo>
        <Descrizione>ACE CANDEGGINA BLU DENSO PIU'1LT</Descrizione>
        <Quantita>1.0000</Quantita>
        <UnitaMisura>PZ</UnitaMisura>
        <PrezzoUnitario>1.6311</PrezzoUnitario>
        <PrezzoTotale>1.6311</PrezzoTotale>
        <AliquotaIVA>22.00</AliquotaIVA>
      </DettaglioLinee>
      <DettaglioLinee>
        <NumeroLinea>8</NumeroLinea>
        <CodiceArticolo>
          <CodiceTipo>EAN</CodiceTipo>
          <CodiceValore>8001480408456</CodiceValore>
        </CodiceArticolo>
        <Descrizione>LINES SETA ULTRA X16</Descrizione>
        <Quantita>1.0000</Quantita>
        <UnitaMisura>PZ</UnitaMisura>
        <PrezzoUnitario>2.3714</PrezzoUnitario>
        <PrezzoTotale>2.3714</PrezzoTotale>
        <AliquotaIVA>5.00</AliquotaIVA>
      </DettaglioLinee>
      <DettaglioLinee>
        <NumeroLinea>9</NumeroLinea>
        <CodiceArticolo>
          <CodiceTipo>EAN</CodiceTipo>
          <CodiceValore>8006540920916</CodiceValore>
        </CodiceArticolo>
        <Descrizione>DASH FUSTINO 23MIS 1,265/KG</Descrizione>
        <Quantita>1.0000</Quantita>
        <UnitaMisura>PZ</UnitaMisura>
        <PrezzoUnitario>7.1230</PrezzoUnitario>
        <PrezzoTotale>7.1230</PrezzoTotale>
        <AliquotaIVA>22.00</AliquotaIVA>
      </DettaglioLinee>
      <DettaglioLinee>
        <NumeroLinea>10</NumeroLinea>
        <CodiceArticolo>
          <CodiceTipo>EAN</CodiceTipo>
          <CodiceValore>8033011700340</CodiceValore>
        </CodiceArticolo>
        <Descrizione>CORONA IGIENICA ORO PZ.4</Descrizione>
        <Quantita>1.0000</Quantita>
        <UnitaMisura>PZ</UnitaMisura>
        <PrezzoUnitario>2.0492</PrezzoUnitario>
        <PrezzoTotale>2.0492</PrezzoTotale>
        <AliquotaIVA>22.00</AliquotaIVA>
      </DettaglioLinee>
      <DettaglioLinee>
        <NumeroLinea>11</NumeroLinea>
        <CodiceArticolo>
          <CodiceTipo>EAN</CodiceTipo>
          <CodiceValore>8001480408456</CodiceValore>
        </CodiceArticolo>
        <Descrizione>LINES SETA ULTRA X16</Descrizione>
        <Quantita>1.0000</Quantita>
        <UnitaMisura>PZ</UnitaMisura>
        <PrezzoUnitario>2.3714</PrezzoUnitario>
        <PrezzoTotale>2.3714</PrezzoTotale>
        <AliquotaIVA>5.00</AliquotaIVA>
      </DettaglioLinee>
      <DettaglioLinee>
        <NumeroLinea>12</NumeroLinea>
        <CodiceArticolo>
          <CodiceTipo>EAN</CodiceTipo>
          <CodiceValore>8006540791189</CodiceValore>
        </CodiceArticolo>
        <Descrizione>LENOR UNSTOPPABLES DASH GR.210</Descrizione>
        <Quantita>1.0000</Quantita>
        <UnitaMisura>PZ</UnitaMisura>
        <PrezzoUnitario>3.1967</PrezzoUnitario>
        <PrezzoTotale>3.1967</PrezzoTotale>
        <AliquotaIVA>22.00</AliquotaIVA>
      </DettaglioLinee>
      <DettaglioLinee>
        <NumeroLinea>13</NumeroLinea>
        <CodiceArticolo>
          <CodiceTipo>EAN</CodiceTipo>
          <CodiceValore>8006540927434</CodiceValore>
        </CodiceArticolo>
        <Descrizione>DASH LIQ. LAV. 58LAV. COLORE</Descrizione>
        <Quantita>1.0000</Quantita>
        <UnitaMisura>PZ</UnitaMisura>
        <PrezzoUnitario>10.2459</PrezzoUnitario>
        <PrezzoTotale>10.2459</PrezzoTotale>
        <AliquotaIVA>22.00</AliquotaIVA>
      </DettaglioLinee>
      <DettaglioLinee>
        <NumeroLinea>14</NumeroLinea>
        <CodiceArticolo>
          <CodiceTipo>EAN</CodiceTipo>
          <CodiceValore>8057502407976</CodiceValore>
        </CodiceArticolo>
        <Descrizione>SCRUB CORPO AI SALI 250ML</Descrizione>
        <Quantita>1.0000</Quantita>
        <UnitaMisura>PZ</UnitaMisura>
        <PrezzoUnitario>3.6885</PrezzoUnitario>
        <PrezzoTotale>3.6885</PrezzoTotale>
        <AliquotaIVA>22.00</AliquotaIVA>
      </DettaglioLinee>
      <DettaglioLinee>
        <NumeroLinea>15</NumeroLinea>
        <CodiceArticolo>
          <CodiceTipo>EAN</CodiceTipo>
          <CodiceValore>8720181340543</CodiceValore>
        </CodiceArticolo>
        <Descrizione>DOVE DEO SPRAY 200 ML. MEN FRESH</Descrizione>
        <Quantita>1.0000</Quantita>
        <UnitaMisura>PZ</UnitaMisura>
        <PrezzoUnitario>2.2951</PrezzoUnitario>
        <PrezzoTotale>2.2951</PrezzoTotale>
        <AliquotaIVA>22.00</AliquotaIVA>
      </DettaglioLinee>
      <DettaglioLinee>
        <NumeroLinea>16</NumeroLinea>
        <CodiceArticolo>
          <CodiceTipo>EAN</CodiceTipo>
          <CodiceValore>8001480408449</CodiceValore>
        </CodiceArticolo>
        <Descrizione>LINES SETA ULTRA X8 NOTTE CON ALI</Descrizione>
        <Quantita>1.0000</Quantita>
        <UnitaMisura>PZ</UnitaMisura>
        <PrezzoUnitario>1.7273</PrezzoUnitario>
        <PrezzoTotale>1.7273</PrezzoTotale>
        <AliquotaIVA>10.00</AliquotaIVA>
      </DettaglioLinee>
      <DettaglioLinee>
        <NumeroLinea>17</NumeroLinea>
        <CodiceArticolo>
          <CodiceTipo>EAN</CodiceTipo>
          <CodiceValore>8001841584645</CodiceValore>
        </CodiceArticolo>
        <Descrizione>PANTENE BALSAMO 180ML LISCI SETA 0% COLORANTI</Descrizione>
        <Quantita>1.0000</Quantita>
        <UnitaMisura>PZ</UnitaMisura>
        <PrezzoUnitario>2.0492</PrezzoUnitario>
        <PrezzoTotale>2.0492</PrezzoTotale>
        <AliquotaIVA>22.00</AliquotaIVA>
      </DettaglioLinee>
      <DettaglioLinee>
        <NumeroLinea>18</NumeroLinea>
        <CodiceArticolo>
          <CodiceTipo>EAN</CodiceTipo>
          <CodiceValore>8054144600215</CodiceValore>
        </CodiceArticolo>
        <Descrizione>bicchieri caffe monouso di carta 75ml</Descrizione>
        <Quantita>1.0000</Quantita>
        <UnitaMisura>PZ</UnitaMisura>
        <PrezzoUnitario>0.6475</PrezzoUnitario>
        <PrezzoTotale>0.6475</PrezzoTotale>
        <AliquotaIVA>22.00</AliquotaIVA>
      </DettaglioLinee>
      <DettaglioLinee>
        <NumeroLinea>19</NumeroLinea>
        <CodiceArticolo>
          <CodiceTipo>EAN</CodiceTipo>
          <CodiceValore>8008990055132</CodiceValore>
        </CodiceArticolo>
        <Descrizione>ARIX 3 PAGLIETTE SPEC.INOX</Descrizione>
        <Quantita>1.0000</Quantita>
        <UnitaMisura>PZ</UnitaMisura>
        <PrezzoUnitario>1.3934</PrezzoUnitario>
        <PrezzoTotale>1.3934</PrezzoTotale>
        <AliquotaIVA>22.00</AliquotaIVA>
      </DettaglioLinee>
      <DettaglioLinee>
        <NumeroLinea>20</NumeroLinea>
        <CodiceArticolo>
          <CodiceTipo>EAN</CodiceTipo>
          <CodiceValore>8001940005133</CodiceValore>
        </CodiceArticolo>
        <Descrizione>WETTEX PANNO EXTRA MULTIUSO</Descrizione>
        <Quantita>1.0000</Quantita>
        <UnitaMisura>PZ</UnitaMisura>
        <PrezzoUnitario>3.1967</PrezzoUnitario>
        <PrezzoTotale>3.1967</PrezzoTotale>
        <AliquotaIVA>22.00</AliquotaIVA>
      </DettaglioLinee>
      <DettaglioLinee>
        <NumeroLinea>21</NumeroLinea>
        <CodiceArticolo>
          <CodiceTipo>EAN</CodiceTipo>
          <CodiceValore>8001940005133</CodiceValore>
        </CodiceArticolo>
        <Descrizione>WETTEX PANNO EXTRA MULTIUSO</Descrizione>
        <Quantita>1.0000</Quantita>
        <UnitaMisura>PZ</UnitaMisura>
        <PrezzoUnitario>3.1967</PrezzoUnitario>
        <PrezzoTotale>3.1967</PrezzoTotale>
        <AliquotaIVA>22.00</AliquotaIVA>
      </DettaglioLinee>
      <DettaglioLinee>
        <NumeroLinea>22</NumeroLinea>
        <CodiceArticolo>
          <CodiceTipo>EAN</CodiceTipo>
          <CodiceValore>8033011700340</CodiceValore>
        </CodiceArticolo>
        <Descrizione>CORONA IGIENICA ORO PZ.4</Descrizione>
        <Quantita>1.0000</Quantita>
        <UnitaMisura>PZ</UnitaMisura>
        <PrezzoUnitario>2.0492</PrezzoUnitario>
        <PrezzoTotale>2.0492</PrezzoTotale>
        <AliquotaIVA>22.00</AliquotaIVA>
      </DettaglioLinee>
      <DettaglioLinee>
        <NumeroLinea>23</NumeroLinea>
        <CodiceArticolo>
          <CodiceTipo>EAN</CodiceTipo>
          <CodiceValore>8054144600215</CodiceValore>
        </CodiceArticolo>
        <Descrizione>bicchieri caffe monouso di carta 75ml</Descrizione>
        <Quantita>1.0000</Quantita>
        <UnitaMisura>PZ</UnitaMisura>
        <PrezzoUnitario>0.6475</PrezzoUnitario>
        <PrezzoTotale>0.6475</PrezzoTotale>
        <AliquotaIVA>22.00</AliquotaIVA>
      </DettaglioLinee>
      <DettaglioLinee>
        <NumeroLinea>24</NumeroLinea>
        <CodiceArticolo>
          <CodiceTipo>EAN</CodiceTipo>
          <CodiceValore>8032642590177</CodiceValore>
        </CodiceArticolo>
        <Descrizione>IMB BICCHIERI ACQUA 200CC X100</Descrizione>
        <Quantita>1.0000</Quantita>
        <UnitaMisura>PZ</UnitaMisura>
        <PrezzoUnitario>0.7295</PrezzoUnitario>
        <PrezzoTotale>0.7295</PrezzoTotale>
        <AliquotaIVA>22.00</AliquotaIVA>
      </DettaglioLinee>
      <DettaglioLinee>
        <NumeroLinea>25</NumeroLinea>
        <CodiceArticolo>
          <CodiceTipo>EAN</CodiceTipo>
          <CodiceValore>8008260102375</CodiceValore>
        </CodiceArticolo>
        <Descrizione>FOXY ASCIUGONI 2RT MEGA DECORATO</Descrizione>
        <Quantita>1.0000</Quantita>
        <UnitaMisura>PZ</UnitaMisura>
        <PrezzoUnitario>2.0492</PrezzoUnitario>
        <PrezzoTotale>2.0492</PrezzoTotale>
        <AliquotaIVA>22.00</AliquotaIVA>
      </DettaglioLinee>
      <DettaglioLinee>
        <NumeroLinea>26</NumeroLinea>
        <CodiceArticolo>
          <CodiceTipo>EAN</CodiceTipo>
          <CodiceValore>3574660067682</CodiceValore>
        </CodiceArticolo>
        <Descrizione>CAREFREE S/SLIP 40+4PZ.</Descrizione>
        <Quantita>1.0000</Quantita>
        <UnitaMisura>PZ</UnitaMisura>
        <PrezzoUnitario>2.0909</PrezzoUnitario>
        <PrezzoTotale>2.0909</PrezzoTotale>
        <AliquotaIVA>10.00</AliquotaIVA>
      </DettaglioLinee>
      <DettaglioLinee>
        <NumeroLinea>27</NumeroLinea>
        <CodiceArticolo>
          <CodiceTipo>EAN</CodiceTipo>
          <CodiceValore>8720181527920</CodiceValore>
        </CodiceArticolo>
        <Descrizione>DOVE BAGNOSCHIUMA 750 ML ORIGINAL</Descrizione>
        <Quantita>1.0000</Quantita>
        <UnitaMisura>PZ</UnitaMisura>
        <PrezzoUnitario>2.8689</PrezzoUnitario>
        <PrezzoTotale>2.8689</PrezzoTotale>
        <AliquotaIVA>22.00</AliquotaIVA>
      </DettaglioLinee>
      <DettaglioLinee>
        <NumeroLinea>28</NumeroLinea>
        <CodiceArticolo>
          <CodiceTipo>EAN</CodiceTipo>
          <CodiceValore>8002295030528</CodiceValore>
        </CodiceArticolo>
        <Descrizione>MADEL SMACCHIO TUTTO ML.250</Descrizione>
        <Quantita>1.0000</Quantita>
        <UnitaMisura>PZ</UnitaMisura>
        <PrezzoUnitario>1.3115</PrezzoUnitario>
        <PrezzoTotale>1.3115</PrezzoTotale>
        <AliquotaIVA>22.00</AliquotaIVA>
      </DettaglioLinee>
      <DettaglioLinee>
        <NumeroLinea>29</NumeroLinea>
        <CodiceArticolo>
          <CodiceTipo>EAN</CodiceTipo>
          <CodiceValore>8002295030528</CodiceValore>
        </CodiceArticolo>
        <Descrizione>MADEL SMACCHIO TUTTO ML.250</Descrizione>
        <Quantita>1.0000</Quantita>
        <UnitaMisura>PZ</UnitaMisura>
        <PrezzoUnitario>1.3115</PrezzoUnitario>
        <PrezzoTotale>1.3115</PrezzoTotale>
        <AliquotaIVA>22.00</AliquotaIVA>
      </DettaglioLinee>
      <DettaglioLinee>
        <NumeroLinea>30</NumeroLinea>
        <CodiceArticolo>
          <CodiceTipo>EAN</CodiceTipo>
          <CodiceValore>8717163617687</CodiceValore>
        </CodiceArticolo>
        <Descrizione>CIF CREMA 750ML LIMONE</Descrizione>
        <Quantita>1.0000</Quantita>
        <UnitaMisura>PZ</UnitaMisura>
        <PrezzoUnitario>1.7623</PrezzoUnitario>
        <PrezzoTotale>1.7623</PrezzoTotale>
        <AliquotaIVA>22.00</AliquotaIVA>
      </DettaglioLinee>
      <DettaglioLinee>
        <NumeroLinea>31</NumeroLinea>
        <CodiceArticolo>
          <CodiceTipo>EAN</CodiceTipo>
          <CodiceValore>8006540490068</CodiceValore>
        </CodiceArticolo>
        <Descrizione>FAIRY GEL OCEAN REGOLARE ML.60</Descrizione>
        <Quantita>1.0000</Quantita>
        <UnitaMisura>PZ</UnitaMisura>
        <PrezzoUnitario>3.2705</PrezzoUnitario>
        <PrezzoTotale>3.2705</PrezzoTotale>
        <AliquotaIVA>22.00</AliquotaIVA>
      </DettaglioLinee>
      <DettaglioLinee>
        <NumeroLinea>32</NumeroLinea>
        <CodiceArticolo>
          <CodiceTipo>EAN</CodiceTipo>
          <CodiceValore>8008731005594</CodiceValore>
        </CodiceArticolo>
        <Descrizione>QUASAR VETRI 580ML TRIGGER EXTRA PROFUM.</Descrizione>
        <Quantita>1.0000</Quantita>
        <UnitaMisura>PZ</UnitaMisura>
        <PrezzoUnitario>2.0410</PrezzoUnitario>
        <PrezzoTotale>2.0410</PrezzoTotale>
        <AliquotaIVA>22.00</AliquotaIVA>
      </DettaglioLinee>
      <DettaglioLinee>
        <NumeroLinea>33</NumeroLinea>
        <CodiceArticolo>
          <CodiceTipo>EAN</CodiceTipo>
          <CodiceValore>8008731005709</CodiceValore>
        </CodiceArticolo>
        <Descrizione>QUASAR COMPL.580 IGIENIZ.ANIMALI   C4026</Descrizione>
        <Quantita>1.0000</Quantita>
        <UnitaMisura>PZ</UnitaMisura>
        <PrezzoUnitario>1.8852</PrezzoUnitario>
        <PrezzoTotale>1.8852</PrezzoTotale>
        <AliquotaIVA>22.00</AliquotaIVA>
      </DettaglioLinee>
      <DettaglioLinee>
        <NumeroLinea>34</NumeroLinea>
        <CodiceArticolo>
          <CodiceTipo>EAN</CodiceTipo>
          <CodiceValore>8717163997345</CodiceValore>
        </CodiceArticolo>
        <Descrizione>DOVE DEO SPRAY 250ML ORIGINAL</Descrizione>
        <Quantita>1.0000</Quantita>
        <UnitaMisura>PZ</UnitaMisura>
        <PrezzoUnitario>2.2951</PrezzoUnitario>
        <PrezzoTotale>2.2951</PrezzoTotale>
        <AliquotaIVA>22.00</AliquotaIVA>
      </DettaglioLinee>
      <DettaglioLinee>
        <NumeroLinea>35</NumeroLinea>
        <CodiceArticolo>
          <CodiceTipo>EAN</CodiceTipo>
          <CodiceValore>8002295030528</CodiceValore>
        </CodiceArticolo>
        <Descrizione>MADEL SMACCHIO TUTTO ML.250</Descrizione>
        <Quantita>1.0000</Quantita>
        <UnitaMisura>PZ</UnitaMisura>
        <PrezzoUnitario>1.3115</PrezzoUnitario>
        <PrezzoTotale>1.3115</PrezzoTotale>
        <AliquotaIVA>22.00</AliquotaIVA>
      </DettaglioLinee>
      <DettaglioLinee>
        <NumeroLinea>36</NumeroLinea>
        <CodiceArticolo>
          <CodiceTipo>EAN</CodiceTipo>
          <CodiceValore>8002295030528</CodiceValore>
        </CodiceArticolo>
        <Descrizione>MADEL SMACCHIO TUTTO ML.250</Descrizione>
        <Quantita>1.0000</Quantita>
        <UnitaMisura>PZ</UnitaMisura>
        <PrezzoUnitario>1.3115</PrezzoUnitario>
        <PrezzoTotale>1.3115</PrezzoTotale>
        <AliquotaIVA>22.00</AliquotaIVA>
      </DettaglioLinee>
      <DettaglioLinee>
        <NumeroLinea>37</NumeroLinea>
        <CodiceArticolo>
          <CodiceTipo>EAN</CodiceTipo>
          <CodiceValore>8051511774838</CodiceValore>
        </CodiceArticolo>
        <Descrizione>SPINGIACQUA PLASTICA 33CM</Descrizione>
        <Quantita>1.0000</Quantita>
        <UnitaMisura>PZ</UnitaMisura>
        <PrezzoUnitario>1.3934</PrezzoUnitario>
        <PrezzoTotale>1.3934</PrezzoTotale>
        <AliquotaIVA>22.00</AliquotaIVA>
      </DettaglioLinee>
      <DettaglioLinee>
        <NumeroLinea>38</NumeroLinea>
        <CodiceArticolo>
          <CodiceTipo>EAN</CodiceTipo>
          <CodiceValore>8015194518387</CodiceValore>
        </CodiceArticolo>
        <Descrizione>CHANTE CLAIR SGRASS. 625 ML COMPLETO CANDEG.FRESCO</Descrizione>
        <Quantita>1.0000</Quantita>
        <UnitaMisura>PZ</UnitaMisura>
        <PrezzoUnitario>1.6311</PrezzoUnitario>
        <PrezzoTotale>1.6311</PrezzoTotale>
        <AliquotaIVA>22.00</AliquotaIVA>
      </DettaglioLinee>
      <DettaglioLinee>
        <NumeroLinea>39</NumeroLinea>
        <CodiceArticolo>
          <CodiceTipo>EAN</CodiceTipo>
          <CodiceValore>8003510004249</CodiceValore>
        </CodiceArticolo>
        <Descrizione>MALIZIA BAGNO 1LT LATTE</Descrizione>
        <Quantita>1.0000</Quantita>
        <UnitaMisura>PZ</UnitaMisura>
        <PrezzoUnitario>1.6311</PrezzoUnitario>
        <PrezzoTotale>1.6311</PrezzoTotale>
        <AliquotaIVA>22.00</AliquotaIVA>
      </DettaglioLinee>
      <DettaglioLinee>
        <NumeroLinea>40</NumeroLinea>
        <CodiceArticolo>
          <CodiceTipo>EAN</CodiceTipo>
          <CodiceValore>8000580203329</CodiceValore>
        </CodiceArticolo>
        <Descrizione>FINISH SALE 1KG</Descrizione>
        <Quantita>1.0000</Quantita>
        <UnitaMisura>PZ</UnitaMisura>
        <PrezzoUnitario>1.3115</PrezzoUnitario>
        <PrezzoTotale>1.3115</PrezzoTotale>
        <AliquotaIVA>22.00</AliquotaIVA>
      </DettaglioLinee>
      <DettaglioLinee>
        <NumeroLinea>41</NumeroLinea>
        <CodiceArticolo>
          <CodiceTipo>EAN</CodiceTipo>
          <CodiceValore>4023103073029</CodiceValore>
        </CodiceArticolo>
        <Descrizione>VILEDA PANNO MICROFIBRA UNIVER</Descrizione>
        <Quantita>1.0000</Quantita>
        <UnitaMisura>PZ</UnitaMisura>
        <PrezzoUnitario>1.8033</PrezzoUnitario>
        <PrezzoTotale>1.8033</PrezzoTotale>
        <AliquotaIVA>22.00</AliquotaIVA>
      </DettaglioLinee>
      <DettaglioLinee>
        <NumeroLinea>42</NumeroLinea>
        <CodiceArticolo>
          <CodiceTipo>EAN</CodiceTipo>
          <CodiceValore>4023103073029</CodiceValore>
        </CodiceArticolo>
        <Descrizione>VILEDA PANNO MICROFIBRA UNIVER</Descrizione>
        <Quantita>1.0000</Quantita>
        <UnitaMisura>PZ</UnitaMisura>
        <PrezzoUnitario>1.8033</PrezzoUnitario>
        <PrezzoTotale>1.8033</PrezzoTotale>
        <AliquotaIVA>22.00</AliquotaIVA>
      </DettaglioLinee>
      <DettaglioLinee>
        <NumeroLinea>43</NumeroLinea>
        <CodiceArticolo>
          <CodiceTipo>EAN</CodiceTipo>
          <CodiceValore>8720181389504</CodiceValore>
        </CodiceArticolo>
        <Descrizione>SVELTO PIATTI LIMONE 1030 ML ( 930+100 ML )</Descrizione>
        <Quantita>1.0000</Quantita>
        <UnitaMisura>PZ</UnitaMisura>
        <PrezzoUnitario>1.2213</PrezzoUnitario>
        <PrezzoTotale>1.2213</PrezzoTotale>
        <AliquotaIVA>22.00</AliquotaIVA>
      </DettaglioLinee>
      <DettaglioLinee>
        <NumeroLinea>44</NumeroLinea>
        <CodiceArticolo>
          <CodiceTipo>EAN</CodiceTipo>
          <CodiceValore>8001480022287</CodiceValore>
        </CodiceArticolo>
        <Descrizione>ACE WC GEL 700ML BREZZA MARINA</Descrizione>
        <Quantita>1.0000</Quantita>
        <UnitaMisura>PZ</UnitaMisura>
        <PrezzoUnitario>1.4754</PrezzoUnitario>
        <PrezzoTotale>1.4754</PrezzoTotale>
        <AliquotaIVA>22.00</AliquotaIVA>
      </DettaglioLinee>
      <DettaglioLinee>
        <NumeroLinea>45</NumeroLinea>
        <CodiceArticolo>
          <CodiceTipo>EAN</CodiceTipo>
          <CodiceValore>8015194518387</CodiceValore>
        </CodiceArticolo>
        <Descrizione>CHANTE CLAIR SGRASS. 625 ML COMPLETO CANDEG.FRESCO</Descrizione>
        <Quantita>1.0000</Quantita>
        <UnitaMisura>PZ</UnitaMisura>
        <PrezzoUnitario>1.6311</PrezzoUnitario>
        <PrezzoTotale>1.6311</PrezzoTotale>
        <AliquotaIVA>22.00</AliquotaIVA>
      </DettaglioLinee>
      <DettaglioLinee>
        <NumeroLinea>46</NumeroLinea>
        <CodiceArticolo>
          <CodiceTipo>EAN</CodiceTipo>
          <CodiceValore>8718951567795</CodiceValore>
        </CodiceArticolo>
        <Descrizione>AJAX PAVIMENTI CASA SICURA ML.</Descrizione>
        <Quantita>1.0000</Quantita>
        <UnitaMisura>PZ</UnitaMisura>
        <PrezzoUnitario>2.0492</PrezzoUnitario>
        <PrezzoTotale>2.0492</PrezzoTotale>
        <AliquotaIVA>22.00</AliquotaIVA>
      </DettaglioLinee>
      <DettaglioLinee>
        <NumeroLinea>47</NumeroLinea>
        <CodiceArticolo>
          <CodiceTipo>EAN</CodiceTipo>
          <CodiceValore>8015194522964</CodiceValore>
        </CodiceArticolo>
        <Descrizione>CHANT.SGR.EROG.C/BICARx1P</Descrizione>
        <Quantita>1.0000</Quantita>
        <UnitaMisura>PZ</UnitaMisura>
        <PrezzoUnitario>1.6311</PrezzoUnitario>
        <PrezzoTotale>1.6311</PrezzoTotale>
        <AliquotaIVA>22.00</AliquotaIVA>
      </DettaglioLinee>
      <DettaglioLinee>
        <NumeroLinea>48</NumeroLinea>
        <Descrizione>PANTENE PRO/V</Descrizione>
        <Quantita>1.0000</Quantita>
        <UnitaMisura>PZ</UnitaMisura>
        <PrezzoUnitario>2.6230</PrezzoUnitario>
        <PrezzoTotale>2.6230</PrezzoTotale>
        <AliquotaIVA>22.00</AliquotaIVA>
      </DettaglioLinee>
      <DatiRiepilogo>
        <AliquotaIVA>5.00</AliquotaIVA>
        <ImponibileImporto>4.74</ImponibileImporto>
        <Imposta>0.24</Imposta>
      </DatiRiepilogo>
      <DatiRiepilogo>
        <AliquotaIVA>22.00</AliquotaIVA>
        <ImponibileImporto>106.25</ImponibileImporto>
        <Imposta>23.37</Imposta>
      </DatiRiepilogo>
      <DatiRiepilogo>
        <AliquotaIVA>10.00</AliquotaIVA>
        <ImponibileImporto>3.82</ImponibileImporto>
        <Imposta>0.38</Imposta>
      </DatiRiepilogo>
    </DatiBeniServizi>
    <DatiPagamento>
      <CondizioniPagamento>TP02</CondizioniPagamento>
      <DettaglioPagamento>
        <ModalitaPagamento>MP08</ModalitaPagamento>
        <ImportoPagamento>138.80</ImportoPagamento>
      </DettaglioPagamento>
    </DatiPagamento>
  </FatturaElettronicaBody>
</p:FatturaElettronica>